odp_gent/__init__.py
odp_gent/exceptions.py
odp_gent/models.py
odp_gent/odp_gent.py
odp_gent/py.typed
odp_gent-0.4.0.dist-info/LICENSE
odp_gent-0.4.0.dist-info/METADATA
odp_gent-0.4.0.dist-info/WHEEL
odp_gent-0.4.0.dist-info/RECORD
